{
    "processed": "timestamp failed at play environment setup timestamp task enable guest ip hack on esxi host ip address fatal localhost failed failed to transfer file to root ansible tmp ansible local number bsi number qhn tmpibjvwhll vmfs volumes data store number ansible tmp hex id number number timestamp ansi ball z command python warning permanently added ip address ecdsa to the list of known hosts dd can t open vmfs volumes data store number ansible tmp hex id number number timestamp ansi ball z command python operation not permitted",
    "detail": {
        "testcase": {
            "confidence": 0.9994503259658813,
            "features": [
                [
                    "timestamp",
                    0.14950354402272834
                ],
                [
                    "failed",
                    0.0742620031522365
                ],
                [
                    "at",
                    -0.009391293556986074
                ],
                [
                    "play",
                    -0.019663268632562608
                ],
                [
                    "environment",
                    0.12211419541355115
                ],
                [
                    "setup",
                    0.04958348505310333
                ],
                [
                    "timestamp",
                    0.14206572017509342
                ],
                [
                    "task",
                    -0.027369357916951123
                ],
                [
                    "enable",
                    -0.04006843672915595
                ],
                [
                    "guest",
                    -0.17421123756468837
                ],
                [
                    "ip",
                    0.03524257995677303
                ],
                [
                    "hack",
                    0.07499051266357523
                ],
                [
                    "on",
                    -0.2151825481430594
                ],
                [
                    "esxi",
                    -0.01267886204700855
                ],
                [
                    "host",
                    0.06458804208618478
                ],
                [
                    "ip",
                    -0.15444122897102544
                ],
                [
                    "address",
                    -0.15287760857617524
                ],
                [
                    "fatal",
                    0.09914444222297086
                ],
                [
                    "localhost",
                    0.07638054351936671
                ],
                [
                    "failed",
                    0.03870202851009774
                ],
                [
                    "failed",
                    0.02290030391372178
                ],
                [
                    "to",
                    0.06953096817744338
                ],
                [
                    "transfer",
                    -0.013533133206303501
                ],
                [
                    "file",
                    -0.03932451073592629
                ],
                [
                    "to",
                    -0.13005719804422916
                ],
                [
                    "root",
                    0.015241564685375618
                ],
                [
                    "ansible",
                    0.04931942026783885
                ],
                [
                    "tmp",
                    -0.039507982655192626
                ],
                [
                    "ansible",
                    0.06255233172977197
                ],
                [
                    "local",
                    0.024146991391113152
                ],
                [
                    "number",
                    0.07703978909252088
                ],
                [
                    "bsi",
                    -0.0663221089335533
                ],
                [
                    "number",
                    -0.0239649945349695
                ],
                [
                    "qhn",
                    0.013525309541205512
                ],
                [
                    "tmpibjvwhll",
                    0.03918805229020169
                ],
                [
                    "vmfs",
                    0.007739054257622065
                ],
                [
                    "volumes",
                    0.1536680561138319
                ],
                [
                    "data",
                    0.0014121087615831802
                ],
                [
                    "store",
                    0.0313101269919723
                ],
                [
                    "number",
                    0.06538563470761471
                ],
                [
                    "ansible",
                    0.06303029444158513
                ],
                [
                    "tmp",
                    -0.09265621493846417
                ],
                [
                    "hex",
                    0.1467725477701933
                ],
                [
                    "id",
                    0.1417070729852672
                ],
                [
                    "number",
                    0.02671194005773883
                ],
                [
                    "number",
                    -0.10148903697267016
                ],
                [
                    "timestamp",
                    -0.17375628212877609
                ],
                [
                    "ansi",
                    -0.0697563200607687
                ],
                [
                    "ball",
                    -0.017094655996003374
                ],
                [
                    "z",
                    -0.14237944936999683
                ],
                [
                    "command",
                    -0.19694120939103796
                ],
                [
                    "python",
                    -0.04794062223460839
                ],
                [
                    "warning",
                    -0.15347541351257146
                ],
                [
                    "permanently",
                    -0.1641794426355038
                ],
                [
                    "added",
                    0.11507103928059291
                ],
                [
                    "ip",
                    0.046076381389547276
                ],
                [
                    "address",
                    -0.0961625392307379
                ],
                [
                    "ecdsa",
                    -0.11862614922335811
                ],
                [
                    "to",
                    -0.10855869056703332
                ],
                [
                    "the",
                    0.11375510539468657
                ],
                [
                    "list",
                    0.11881951889964858
                ],
                [
                    "of",
                    -0.030936878753848162
                ],
                [
                    "known",
                    0.030220087707566363
                ],
                [
                    "hosts",
                    -0.007360312871366101
                ],
                [
                    "dd",
                    -0.03197897050188139
                ],
                [
                    "can",
                    -0.041739497616535386
                ],
                [
                    "t",
                    0.04252941679961295
                ],
                [
                    "open",
                    -0.01967067585949372
                ],
                [
                    "vmfs",
                    -0.19071570364445714
                ],
                [
                    "volumes",
                    0.11251768558918256
                ],
                [
                    "data",
                    -0.04174079911997135
                ],
                [
                    "store",
                    0.14573618900395335
                ],
                [
                    "number",
                    -0.005106775118086935
                ],
                [
                    "ansible",
                    0.14036180418642658
                ],
                [
                    "tmp",
                    0.016369465351986145
                ],
                [
                    "hex",
                    0.09627237826814654
                ],
                [
                    "id",
                    -0.03434879348462162
                ],
                [
                    "number",
                    -0.015451790880794736
                ],
                [
                    "number",
                    -0.01597545183036411
                ],
                [
                    "timestamp",
                    0.03957114732546424
                ],
                [
                    "ansi",
                    -0.12871894739544992
                ],
                [
                    "ball",
                    0.014559979151313062
                ],
                [
                    "z",
                    0.0846440591917174
                ],
                [
                    "command",
                    -0.06083410109186911
                ],
                [
                    "python",
                    0.022927785688474242
                ],
                [
                    "operation",
                    0.07870537514439574
                ],
                [
                    "not",
                    0.05962669406545201
                ],
                [
                    "permitted",
                    -0.011568398840893048
                ]
            ]
        },
        "targetvm": {
            "confidence": 0.00030073829111643136,
            "features": [
                [
                    "timestamp",
                    -0.14950354402272834
                ],
                [
                    "failed",
                    -0.0742620031522365
                ],
                [
                    "at",
                    0.009391293556986074
                ],
                [
                    "play",
                    0.019663268632562608
                ],
                [
                    "environment",
                    -0.12211419541355115
                ],
                [
                    "setup",
                    -0.04958348505310333
                ],
                [
                    "timestamp",
                    -0.14206572017509342
                ],
                [
                    "task",
                    0.027369357916951123
                ],
                [
                    "enable",
                    0.04006843672915595
                ],
                [
                    "guest",
                    0.17421123756468837
                ],
                [
                    "ip",
                    -0.03524257995677303
                ],
                [
                    "hack",
                    -0.07499051266357523
                ],
                [
                    "on",
                    0.2151825481430594
                ],
                [
                    "esxi",
                    0.01267886204700855
                ],
                [
                    "host",
                    -0.06458804208618478
                ],
                [
                    "ip",
                    0.15444122897102544
                ],
                [
                    "address",
                    0.15287760857617524
                ],
                [
                    "fatal",
                    -0.09914444222297086
                ],
                [
                    "localhost",
                    -0.07638054351936671
                ],
                [
                    "failed",
                    -0.03870202851009774
                ],
                [
                    "failed",
                    -0.02290030391372178
                ],
                [
                    "to",
                    -0.06953096817744338
                ],
                [
                    "transfer",
                    0.013533133206303501
                ],
                [
                    "file",
                    0.03932451073592629
                ],
                [
                    "to",
                    0.13005719804422916
                ],
                [
                    "root",
                    -0.015241564685375618
                ],
                [
                    "ansible",
                    -0.04931942026783885
                ],
                [
                    "tmp",
                    0.039507982655192626
                ],
                [
                    "ansible",
                    -0.06255233172977197
                ],
                [
                    "local",
                    -0.024146991391113152
                ],
                [
                    "number",
                    -0.07703978909252088
                ],
                [
                    "bsi",
                    0.0663221089335533
                ],
                [
                    "number",
                    0.0239649945349695
                ],
                [
                    "qhn",
                    -0.013525309541205512
                ],
                [
                    "tmpibjvwhll",
                    -0.03918805229020169
                ],
                [
                    "vmfs",
                    -0.007739054257622065
                ],
                [
                    "volumes",
                    -0.1536680561138319
                ],
                [
                    "data",
                    -0.0014121087615831802
                ],
                [
                    "store",
                    -0.0313101269919723
                ],
                [
                    "number",
                    -0.06538563470761471
                ],
                [
                    "ansible",
                    -0.06303029444158513
                ],
                [
                    "tmp",
                    0.09265621493846417
                ],
                [
                    "hex",
                    -0.1467725477701933
                ],
                [
                    "id",
                    -0.1417070729852672
                ],
                [
                    "number",
                    -0.02671194005773883
                ],
                [
                    "number",
                    0.10148903697267016
                ],
                [
                    "timestamp",
                    0.17375628212877609
                ],
                [
                    "ansi",
                    0.0697563200607687
                ],
                [
                    "ball",
                    0.017094655996003374
                ],
                [
                    "z",
                    0.14237944936999683
                ],
                [
                    "command",
                    0.19694120939103796
                ],
                [
                    "python",
                    0.04794062223460839
                ],
                [
                    "warning",
                    0.15347541351257146
                ],
                [
                    "permanently",
                    0.1641794426355038
                ],
                [
                    "added",
                    -0.11507103928059291
                ],
                [
                    "ip",
                    -0.046076381389547276
                ],
                [
                    "address",
                    0.0961625392307379
                ],
                [
                    "ecdsa",
                    0.11862614922335811
                ],
                [
                    "to",
                    0.10855869056703332
                ],
                [
                    "the",
                    -0.11375510539468657
                ],
                [
                    "list",
                    -0.11881951889964858
                ],
                [
                    "of",
                    0.030936878753848162
                ],
                [
                    "known",
                    -0.030220087707566363
                ],
                [
                    "hosts",
                    0.007360312871366101
                ],
                [
                    "dd",
                    0.03197897050188139
                ],
                [
                    "can",
                    0.041739497616535386
                ],
                [
                    "t",
                    -0.04252941679961295
                ],
                [
                    "open",
                    0.01967067585949372
                ],
                [
                    "vmfs",
                    0.19071570364445714
                ],
                [
                    "volumes",
                    -0.11251768558918256
                ],
                [
                    "data",
                    0.04174079911997135
                ],
                [
                    "store",
                    -0.14573618900395335
                ],
                [
                    "number",
                    0.005106775118086935
                ],
                [
                    "ansible",
                    -0.14036180418642658
                ],
                [
                    "tmp",
                    -0.016369465351986145
                ],
                [
                    "hex",
                    -0.09627237826814654
                ],
                [
                    "id",
                    0.03434879348462162
                ],
                [
                    "number",
                    0.015451790880794736
                ],
                [
                    "number",
                    0.01597545183036411
                ],
                [
                    "timestamp",
                    -0.03957114732546424
                ],
                [
                    "ansi",
                    0.12871894739544992
                ],
                [
                    "ball",
                    -0.014559979151313062
                ],
                [
                    "z",
                    -0.0846440591917174
                ],
                [
                    "command",
                    0.06083410109186911
                ],
                [
                    "python",
                    -0.022927785688474242
                ],
                [
                    "operation",
                    -0.07870537514439574
                ],
                [
                    "not",
                    -0.05962669406545201
                ],
                [
                    "permitted",
                    0.011568398840893048
                ]
            ]
        },
        "testbed": {
            "confidence": 6.162025238154456e-05,
            "features": [
                [
                    "timestamp",
                    0.0
                ],
                [
                    "failed",
                    0.0
                ],
                [
                    "at",
                    0.0
                ],
                [
                    "play",
                    0.0
                ],
                [
                    "environment",
                    0.0
                ],
                [
                    "setup",
                    0.0
                ],
                [
                    "timestamp",
                    0.0
                ],
                [
                    "task",
                    0.0
                ],
                [
                    "enable",
                    0.0
                ],
                [
                    "guest",
                    0.0
                ],
                [
                    "ip",
                    0.0
                ],
                [
                    "hack",
                    0.0
                ],
                [
                    "on",
                    0.0
                ],
                [
                    "esxi",
                    0.0
                ],
                [
                    "host",
                    0.0
                ],
                [
                    "ip",
                    0.0
                ],
                [
                    "address",
                    0.0
                ],
                [
                    "fatal",
                    0.0
                ],
                [
                    "localhost",
                    0.0
                ],
                [
                    "failed",
                    0.0
                ],
                [
                    "failed",
                    0.0
                ],
                [
                    "to",
                    0.0
                ],
                [
                    "transfer",
                    0.0
                ],
                [
                    "file",
                    0.0
                ],
                [
                    "to",
                    0.0
                ],
                [
                    "root",
                    0.0
                ],
                [
                    "ansible",
                    0.0
                ],
                [
                    "tmp",
                    0.0
                ],
                [
                    "ansible",
                    0.0
                ],
                [
                    "local",
                    0.0
                ],
                [
                    "number",
                    0.0
                ],
                [
                    "bsi",
                    0.0
                ],
                [
                    "number",
                    0.0
                ],
                [
                    "qhn",
                    0.0
                ],
                [
                    "tmpibjvwhll",
                    0.0
                ],
                [
                    "vmfs",
                    0.0
                ],
                [
                    "volumes",
                    0.0
                ],
                [
                    "data",
                    0.0
                ],
                [
                    "store",
                    0.0
                ],
                [
                    "number",
                    0.0
                ],
                [
                    "ansible",
                    0.0
                ],
                [
                    "tmp",
                    0.0
                ],
                [
                    "hex",
                    0.0
                ],
                [
                    "id",
                    0.0
                ],
                [
                    "number",
                    0.0
                ],
                [
                    "number",
                    0.0
                ],
                [
                    "timestamp",
                    0.0
                ],
                [
                    "ansi",
                    0.0
                ],
                [
                    "ball",
                    0.0
                ],
                [
                    "z",
                    0.0
                ],
                [
                    "command",
                    0.0
                ],
                [
                    "python",
                    0.0
                ],
                [
                    "warning",
                    0.0
                ],
                [
                    "permanently",
                    0.0
                ],
                [
                    "added",
                    0.0
                ],
                [
                    "ip",
                    0.0
                ],
                [
                    "address",
                    0.0
                ],
                [
                    "ecdsa",
                    0.0
                ],
                [
                    "to",
                    0.0
                ],
                [
                    "the",
                    0.0
                ],
                [
                    "list",
                    0.0
                ],
                [
                    "of",
                    0.0
                ],
                [
                    "known",
                    0.0
                ],
                [
                    "hosts",
                    0.0
                ],
                [
                    "dd",
                    0.0
                ],
                [
                    "can",
                    0.0
                ],
                [
                    "t",
                    0.0
                ],
                [
                    "open",
                    0.0
                ],
                [
                    "vmfs",
                    0.0
                ],
                [
                    "volumes",
                    0.0
                ],
                [
                    "data",
                    0.0
                ],
                [
                    "store",
                    0.0
                ],
                [
                    "number",
                    0.0
                ],
                [
                    "ansible",
                    0.0
                ],
                [
                    "tmp",
                    0.0
                ],
                [
                    "hex",
                    0.0
                ],
                [
                    "id",
                    0.0
                ],
                [
                    "number",
                    0.0
                ],
                [
                    "number",
                    0.0
                ],
                [
                    "timestamp",
                    0.0
                ],
                [
                    "ansi",
                    0.0
                ],
                [
                    "ball",
                    0.0
                ],
                [
                    "z",
                    0.0
                ],
                [
                    "command",
                    0.0
                ],
                [
                    "python",
                    0.0
                ],
                [
                    "operation",
                    0.0
                ],
                [
                    "not",
                    0.0
                ],
                [
                    "permitted",
                    0.0
                ]
            ]
        },
        "usererror": {
            "confidence": 5.476626756717451e-05,
            "features": [
                [
                    "timestamp",
                    0.0
                ],
                [
                    "failed",
                    0.0
                ],
                [
                    "at",
                    0.0
                ],
                [
                    "play",
                    0.0
                ],
                [
                    "environment",
                    0.0
                ],
                [
                    "setup",
                    0.0
                ],
                [
                    "timestamp",
                    0.0
                ],
                [
                    "task",
                    0.0
                ],
                [
                    "enable",
                    0.0
                ],
                [
                    "guest",
                    0.0
                ],
                [
                    "ip",
                    0.0
                ],
                [
                    "hack",
                    0.0
                ],
                [
                    "on",
                    0.0
                ],
                [
                    "esxi",
                    0.0
                ],
                [
                    "host",
                    0.0
                ],
                [
                    "ip",
                    0.0
                ],
                [
                    "address",
                    0.0
                ],
                [
                    "fatal",
                    0.0
                ],
                [
                    "localhost",
                    0.0
                ],
                [
                    "failed",
                    0.0
                ],
                [
                    "failed",
                    0.0
                ],
                [
                    "to",
                    0.0
                ],
                [
                    "transfer",
                    0.0
                ],
                [
                    "file",
                    0.0
                ],
                [
                    "to",
                    0.0
                ],
                [
                    "root",
                    0.0
                ],
                [
                    "ansible",
                    0.0
                ],
                [
                    "tmp",
                    0.0
                ],
                [
                    "ansible",
                    0.0
                ],
                [
                    "local",
                    0.0
                ],
                [
                    "number",
                    0.0
                ],
                [
                    "bsi",
                    0.0
                ],
                [
                    "number",
                    0.0
                ],
                [
                    "qhn",
                    0.0
                ],
                [
                    "tmpibjvwhll",
                    0.0
                ],
                [
                    "vmfs",
                    0.0
                ],
                [
                    "volumes",
                    0.0
                ],
                [
                    "data",
                    0.0
                ],
                [
                    "store",
                    0.0
                ],
                [
                    "number",
                    0.0
                ],
                [
                    "ansible",
                    0.0
                ],
                [
                    "tmp",
                    0.0
                ],
                [
                    "hex",
                    0.0
                ],
                [
                    "id",
                    0.0
                ],
                [
                    "number",
                    0.0
                ],
                [
                    "number",
                    0.0
                ],
                [
                    "timestamp",
                    0.0
                ],
                [
                    "ansi",
                    0.0
                ],
                [
                    "ball",
                    0.0
                ],
                [
                    "z",
                    0.0
                ],
                [
                    "command",
                    0.0
                ],
                [
                    "python",
                    0.0
                ],
                [
                    "warning",
                    0.0
                ],
                [
                    "permanently",
                    0.0
                ],
                [
                    "added",
                    0.0
                ],
                [
                    "ip",
                    0.0
                ],
                [
                    "address",
                    0.0
                ],
                [
                    "ecdsa",
                    0.0
                ],
                [
                    "to",
                    0.0
                ],
                [
                    "the",
                    0.0
                ],
                [
                    "list",
                    0.0
                ],
                [
                    "of",
                    0.0
                ],
                [
                    "known",
                    0.0
                ],
                [
                    "hosts",
                    0.0
                ],
                [
                    "dd",
                    0.0
                ],
                [
                    "can",
                    0.0
                ],
                [
                    "t",
                    0.0
                ],
                [
                    "open",
                    0.0
                ],
                [
                    "vmfs",
                    0.0
                ],
                [
                    "volumes",
                    0.0
                ],
                [
                    "data",
                    0.0
                ],
                [
                    "store",
                    0.0
                ],
                [
                    "number",
                    0.0
                ],
                [
                    "ansible",
                    0.0
                ],
                [
                    "tmp",
                    0.0
                ],
                [
                    "hex",
                    0.0
                ],
                [
                    "id",
                    0.0
                ],
                [
                    "number",
                    0.0
                ],
                [
                    "number",
                    0.0
                ],
                [
                    "timestamp",
                    0.0
                ],
                [
                    "ansi",
                    0.0
                ],
                [
                    "ball",
                    0.0
                ],
                [
                    "z",
                    0.0
                ],
                [
                    "command",
                    0.0
                ],
                [
                    "python",
                    0.0
                ],
                [
                    "operation",
                    0.0
                ],
                [
                    "not",
                    0.0
                ],
                [
                    "permitted",
                    0.0
                ]
            ]
        },
        "infra": {
            "confidence": 5.457544102682732e-05,
            "features": [
                [
                    "timestamp",
                    0.0
                ],
                [
                    "failed",
                    0.0
                ],
                [
                    "at",
                    0.0
                ],
                [
                    "play",
                    0.0
                ],
                [
                    "environment",
                    0.0
                ],
                [
                    "setup",
                    0.0
                ],
                [
                    "timestamp",
                    0.0
                ],
                [
                    "task",
                    0.0
                ],
                [
                    "enable",
                    0.0
                ],
                [
                    "guest",
                    0.0
                ],
                [
                    "ip",
                    0.0
                ],
                [
                    "hack",
                    0.0
                ],
                [
                    "on",
                    0.0
                ],
                [
                    "esxi",
                    0.0
                ],
                [
                    "host",
                    0.0
                ],
                [
                    "ip",
                    0.0
                ],
                [
                    "address",
                    0.0
                ],
                [
                    "fatal",
                    0.0
                ],
                [
                    "localhost",
                    0.0
                ],
                [
                    "failed",
                    0.0
                ],
                [
                    "failed",
                    0.0
                ],
                [
                    "to",
                    0.0
                ],
                [
                    "transfer",
                    0.0
                ],
                [
                    "file",
                    0.0
                ],
                [
                    "to",
                    0.0
                ],
                [
                    "root",
                    0.0
                ],
                [
                    "ansible",
                    0.0
                ],
                [
                    "tmp",
                    0.0
                ],
                [
                    "ansible",
                    0.0
                ],
                [
                    "local",
                    0.0
                ],
                [
                    "number",
                    0.0
                ],
                [
                    "bsi",
                    0.0
                ],
                [
                    "number",
                    0.0
                ],
                [
                    "qhn",
                    0.0
                ],
                [
                    "tmpibjvwhll",
                    0.0
                ],
                [
                    "vmfs",
                    0.0
                ],
                [
                    "volumes",
                    0.0
                ],
                [
                    "data",
                    0.0
                ],
                [
                    "store",
                    0.0
                ],
                [
                    "number",
                    0.0
                ],
                [
                    "ansible",
                    0.0
                ],
                [
                    "tmp",
                    0.0
                ],
                [
                    "hex",
                    0.0
                ],
                [
                    "id",
                    0.0
                ],
                [
                    "number",
                    0.0
                ],
                [
                    "number",
                    0.0
                ],
                [
                    "timestamp",
                    0.0
                ],
                [
                    "ansi",
                    0.0
                ],
                [
                    "ball",
                    0.0
                ],
                [
                    "z",
                    0.0
                ],
                [
                    "command",
                    0.0
                ],
                [
                    "python",
                    0.0
                ],
                [
                    "warning",
                    0.0
                ],
                [
                    "permanently",
                    0.0
                ],
                [
                    "added",
                    0.0
                ],
                [
                    "ip",
                    0.0
                ],
                [
                    "address",
                    0.0
                ],
                [
                    "ecdsa",
                    0.0
                ],
                [
                    "to",
                    0.0
                ],
                [
                    "the",
                    0.0
                ],
                [
                    "list",
                    0.0
                ],
                [
                    "of",
                    0.0
                ],
                [
                    "known",
                    0.0
                ],
                [
                    "hosts",
                    0.0
                ],
                [
                    "dd",
                    0.0
                ],
                [
                    "can",
                    0.0
                ],
                [
                    "t",
                    0.0
                ],
                [
                    "open",
                    0.0
                ],
                [
                    "vmfs",
                    0.0
                ],
                [
                    "volumes",
                    0.0
                ],
                [
                    "data",
                    0.0
                ],
                [
                    "store",
                    0.0
                ],
                [
                    "number",
                    0.0
                ],
                [
                    "ansible",
                    0.0
                ],
                [
                    "tmp",
                    0.0
                ],
                [
                    "hex",
                    0.0
                ],
                [
                    "id",
                    0.0
                ],
                [
                    "number",
                    0.0
                ],
                [
                    "number",
                    0.0
                ],
                [
                    "timestamp",
                    0.0
                ],
                [
                    "ansi",
                    0.0
                ],
                [
                    "ball",
                    0.0
                ],
                [
                    "z",
                    0.0
                ],
                [
                    "command",
                    0.0
                ],
                [
                    "python",
                    0.0
                ],
                [
                    "operation",
                    0.0
                ],
                [
                    "not",
                    0.0
                ],
                [
                    "permitted",
                    0.0
                ]
            ]
        },
        "product": {
            "confidence": 4.4986991269979626e-05,
            "features": [
                [
                    "timestamp",
                    0.0
                ],
                [
                    "failed",
                    0.0
                ],
                [
                    "at",
                    0.0
                ],
                [
                    "play",
                    0.0
                ],
                [
                    "environment",
                    0.0
                ],
                [
                    "setup",
                    0.0
                ],
                [
                    "timestamp",
                    0.0
                ],
                [
                    "task",
                    0.0
                ],
                [
                    "enable",
                    0.0
                ],
                [
                    "guest",
                    0.0
                ],
                [
                    "ip",
                    0.0
                ],
                [
                    "hack",
                    0.0
                ],
                [
                    "on",
                    0.0
                ],
                [
                    "esxi",
                    0.0
                ],
                [
                    "host",
                    0.0
                ],
                [
                    "ip",
                    0.0
                ],
                [
                    "address",
                    0.0
                ],
                [
                    "fatal",
                    0.0
                ],
                [
                    "localhost",
                    0.0
                ],
                [
                    "failed",
                    0.0
                ],
                [
                    "failed",
                    0.0
                ],
                [
                    "to",
                    0.0
                ],
                [
                    "transfer",
                    0.0
                ],
                [
                    "file",
                    0.0
                ],
                [
                    "to",
                    0.0
                ],
                [
                    "root",
                    0.0
                ],
                [
                    "ansible",
                    0.0
                ],
                [
                    "tmp",
                    0.0
                ],
                [
                    "ansible",
                    0.0
                ],
                [
                    "local",
                    0.0
                ],
                [
                    "number",
                    0.0
                ],
                [
                    "bsi",
                    0.0
                ],
                [
                    "number",
                    0.0
                ],
                [
                    "qhn",
                    0.0
                ],
                [
                    "tmpibjvwhll",
                    0.0
                ],
                [
                    "vmfs",
                    0.0
                ],
                [
                    "volumes",
                    0.0
                ],
                [
                    "data",
                    0.0
                ],
                [
                    "store",
                    0.0
                ],
                [
                    "number",
                    0.0
                ],
                [
                    "ansible",
                    0.0
                ],
                [
                    "tmp",
                    0.0
                ],
                [
                    "hex",
                    0.0
                ],
                [
                    "id",
                    0.0
                ],
                [
                    "number",
                    0.0
                ],
                [
                    "number",
                    0.0
                ],
                [
                    "timestamp",
                    0.0
                ],
                [
                    "ansi",
                    0.0
                ],
                [
                    "ball",
                    0.0
                ],
                [
                    "z",
                    0.0
                ],
                [
                    "command",
                    0.0
                ],
                [
                    "python",
                    0.0
                ],
                [
                    "warning",
                    0.0
                ],
                [
                    "permanently",
                    0.0
                ],
                [
                    "added",
                    0.0
                ],
                [
                    "ip",
                    0.0
                ],
                [
                    "address",
                    0.0
                ],
                [
                    "ecdsa",
                    0.0
                ],
                [
                    "to",
                    0.0
                ],
                [
                    "the",
                    0.0
                ],
                [
                    "list",
                    0.0
                ],
                [
                    "of",
                    0.0
                ],
                [
                    "known",
                    0.0
                ],
                [
                    "hosts",
                    0.0
                ],
                [
                    "dd",
                    0.0
                ],
                [
                    "can",
                    0.0
                ],
                [
                    "t",
                    0.0
                ],
                [
                    "open",
                    0.0
                ],
                [
                    "vmfs",
                    0.0
                ],
                [
                    "volumes",
                    0.0
                ],
                [
                    "data",
                    0.0
                ],
                [
                    "store",
                    0.0
                ],
                [
                    "number",
                    0.0
                ],
                [
                    "ansible",
                    0.0
                ],
                [
                    "tmp",
                    0.0
                ],
                [
                    "hex",
                    0.0
                ],
                [
                    "id",
                    0.0
                ],
                [
                    "number",
                    0.0
                ],
                [
                    "number",
                    0.0
                ],
                [
                    "timestamp",
                    0.0
                ],
                [
                    "ansi",
                    0.0
                ],
                [
                    "ball",
                    0.0
                ],
                [
                    "z",
                    0.0
                ],
                [
                    "command",
                    0.0
                ],
                [
                    "python",
                    0.0
                ],
                [
                    "operation",
                    0.0
                ],
                [
                    "not",
                    0.0
                ],
                [
                    "permitted",
                    0.0
                ]
            ]
        },
        "nimbus": {
            "confidence": 3.312609260319732e-05,
            "features": [
                [
                    "timestamp",
                    0.0
                ],
                [
                    "failed",
                    0.0
                ],
                [
                    "at",
                    0.0
                ],
                [
                    "play",
                    0.0
                ],
                [
                    "environment",
                    0.0
                ],
                [
                    "setup",
                    0.0
                ],
                [
                    "timestamp",
                    0.0
                ],
                [
                    "task",
                    0.0
                ],
                [
                    "enable",
                    0.0
                ],
                [
                    "guest",
                    0.0
                ],
                [
                    "ip",
                    0.0
                ],
                [
                    "hack",
                    0.0
                ],
                [
                    "on",
                    0.0
                ],
                [
                    "esxi",
                    0.0
                ],
                [
                    "host",
                    0.0
                ],
                [
                    "ip",
                    0.0
                ],
                [
                    "address",
                    0.0
                ],
                [
                    "fatal",
                    0.0
                ],
                [
                    "localhost",
                    0.0
                ],
                [
                    "failed",
                    0.0
                ],
                [
                    "failed",
                    0.0
                ],
                [
                    "to",
                    0.0
                ],
                [
                    "transfer",
                    0.0
                ],
                [
                    "file",
                    0.0
                ],
                [
                    "to",
                    0.0
                ],
                [
                    "root",
                    0.0
                ],
                [
                    "ansible",
                    0.0
                ],
                [
                    "tmp",
                    0.0
                ],
                [
                    "ansible",
                    0.0
                ],
                [
                    "local",
                    0.0
                ],
                [
                    "number",
                    0.0
                ],
                [
                    "bsi",
                    0.0
                ],
                [
                    "number",
                    0.0
                ],
                [
                    "qhn",
                    0.0
                ],
                [
                    "tmpibjvwhll",
                    0.0
                ],
                [
                    "vmfs",
                    0.0
                ],
                [
                    "volumes",
                    0.0
                ],
                [
                    "data",
                    0.0
                ],
                [
                    "store",
                    0.0
                ],
                [
                    "number",
                    0.0
                ],
                [
                    "ansible",
                    0.0
                ],
                [
                    "tmp",
                    0.0
                ],
                [
                    "hex",
                    0.0
                ],
                [
                    "id",
                    0.0
                ],
                [
                    "number",
                    0.0
                ],
                [
                    "number",
                    0.0
                ],
                [
                    "timestamp",
                    0.0
                ],
                [
                    "ansi",
                    0.0
                ],
                [
                    "ball",
                    0.0
                ],
                [
                    "z",
                    0.0
                ],
                [
                    "command",
                    0.0
                ],
                [
                    "python",
                    0.0
                ],
                [
                    "warning",
                    0.0
                ],
                [
                    "permanently",
                    0.0
                ],
                [
                    "added",
                    0.0
                ],
                [
                    "ip",
                    0.0
                ],
                [
                    "address",
                    0.0
                ],
                [
                    "ecdsa",
                    0.0
                ],
                [
                    "to",
                    0.0
                ],
                [
                    "the",
                    0.0
                ],
                [
                    "list",
                    0.0
                ],
                [
                    "of",
                    0.0
                ],
                [
                    "known",
                    0.0
                ],
                [
                    "hosts",
                    0.0
                ],
                [
                    "dd",
                    0.0
                ],
                [
                    "can",
                    0.0
                ],
                [
                    "t",
                    0.0
                ],
                [
                    "open",
                    0.0
                ],
                [
                    "vmfs",
                    0.0
                ],
                [
                    "volumes",
                    0.0
                ],
                [
                    "data",
                    0.0
                ],
                [
                    "store",
                    0.0
                ],
                [
                    "number",
                    0.0
                ],
                [
                    "ansible",
                    0.0
                ],
                [
                    "tmp",
                    0.0
                ],
                [
                    "hex",
                    0.0
                ],
                [
                    "id",
                    0.0
                ],
                [
                    "number",
                    0.0
                ],
                [
                    "number",
                    0.0
                ],
                [
                    "timestamp",
                    0.0
                ],
                [
                    "ansi",
                    0.0
                ],
                [
                    "ball",
                    0.0
                ],
                [
                    "z",
                    0.0
                ],
                [
                    "command",
                    0.0
                ],
                [
                    "python",
                    0.0
                ],
                [
                    "operation",
                    0.0
                ],
                [
                    "not",
                    0.0
                ],
                [
                    "permitted",
                    0.0
                ]
            ]
        }
    }
}