{
    "processed": "timestamp failed at play vmxnet number network device ops timestamp task apply net plan configuration file for new added nic in ubuntu fatal localhost failed failed to connect to the host via ssh ssh connect to host ip address port number connection timed out",
    "detail": {
        "targetvm": {
            "confidence": 0.9996606111526489,
            "features": [
                [
                    "timestamp",
                    0.00201552445826111
                ],
                [
                    "failed",
                    -0.08253008004685396
                ],
                [
                    "at",
                    -0.04074008628063994
                ],
                [
                    "play",
                    0.011212530223165446
                ],
                [
                    "vmxnet",
                    0.07615493262881312
                ],
                [
                    "number",
                    0.012436422172016633
                ],
                [
                    "network",
                    0.09016681590276343
                ],
                [
                    "device",
                    0.006041716507328065
                ],
                [
                    "ops",
                    -0.05438733565067494
                ],
                [
                    "timestamp",
                    0.05618069801387334
                ],
                [
                    "task",
                    -0.023428340022309396
                ],
                [
                    "apply",
                    -0.04355166966986931
                ],
                [
                    "net",
                    0.011712494809467034
                ],
                [
                    "plan",
                    -0.06145037883646842
                ],
                [
                    "configuration",
                    0.03589442335285347
                ],
                [
                    "file",
                    -0.0936147569479864
                ],
                [
                    "for",
                    0.0798036679541853
                ],
                [
                    "new",
                    0.06891278100813315
                ],
                [
                    "added",
                    -0.10222560088504311
                ],
                [
                    "nic",
                    0.07844948485707902
                ],
                [
                    "in",
                    0.01447428477857486
                ],
                [
                    "ubuntu",
                    -0.008933150999634883
                ],
                [
                    "fatal",
                    -0.026283705712057986
                ],
                [
                    "localhost",
                    -0.01193107580814533
                ],
                [
                    "failed",
                    0.06491035849620753
                ],
                [
                    "failed",
                    -0.03584226903526681
                ],
                [
                    "to",
                    0.06856458368467011
                ],
                [
                    "connect",
                    0.08542982736814059
                ],
                [
                    "to",
                    0.03660748441973413
                ],
                [
                    "the",
                    0.04830905095723659
                ],
                [
                    "host",
                    -0.07267557961222744
                ],
                [
                    "via",
                    0.19595574940010255
                ],
                [
                    "ssh",
                    -0.06926511584227273
                ],
                [
                    "ssh",
                    -0.013439277650760058
                ],
                [
                    "connect",
                    0.16236895020243716
                ],
                [
                    "to",
                    0.014474546044911708
                ],
                [
                    "host",
                    0.03682163397924834
                ],
                [
                    "ip",
                    -0.03896435473882771
                ],
                [
                    "address",
                    0.0951001158224479
                ],
                [
                    "port",
                    0.07882313597018613
                ],
                [
                    "number",
                    -0.03679777141259658
                ],
                [
                    "connection",
                    0.12587551076109704
                ],
                [
                    "timed",
                    0.04207156920061449
                ],
                [
                    "out",
                    0.08664390299972839
                ]
            ]
        },
        "infra": {
            "confidence": 0.00015148166858125478,
            "features": [
                [
                    "timestamp",
                    0.0
                ],
                [
                    "failed",
                    0.0
                ],
                [
                    "at",
                    0.0
                ],
                [
                    "play",
                    0.0
                ],
                [
                    "vmxnet",
                    0.0
                ],
                [
                    "number",
                    0.0
                ],
                [
                    "network",
                    0.0
                ],
                [
                    "device",
                    0.0
                ],
                [
                    "ops",
                    0.0
                ],
                [
                    "timestamp",
                    0.0
                ],
                [
                    "task",
                    0.0
                ],
                [
                    "apply",
                    0.0
                ],
                [
                    "net",
                    0.0
                ],
                [
                    "plan",
                    0.0
                ],
                [
                    "configuration",
                    0.0
                ],
                [
                    "file",
                    0.0
                ],
                [
                    "for",
                    0.0
                ],
                [
                    "new",
                    0.0
                ],
                [
                    "added",
                    0.0
                ],
                [
                    "nic",
                    0.0
                ],
                [
                    "in",
                    0.0
                ],
                [
                    "ubuntu",
                    0.0
                ],
                [
                    "fatal",
                    0.0
                ],
                [
                    "localhost",
                    0.0
                ],
                [
                    "failed",
                    0.0
                ],
                [
                    "failed",
                    0.0
                ],
                [
                    "to",
                    0.0
                ],
                [
                    "connect",
                    0.0
                ],
                [
                    "to",
                    0.0
                ],
                [
                    "the",
                    0.0
                ],
                [
                    "host",
                    0.0
                ],
                [
                    "via",
                    0.0
                ],
                [
                    "ssh",
                    0.0
                ],
                [
                    "ssh",
                    0.0
                ],
                [
                    "connect",
                    0.0
                ],
                [
                    "to",
                    0.0
                ],
                [
                    "host",
                    0.0
                ],
                [
                    "ip",
                    0.0
                ],
                [
                    "address",
                    0.0
                ],
                [
                    "port",
                    0.0
                ],
                [
                    "number",
                    0.0
                ],
                [
                    "connection",
                    0.0
                ],
                [
                    "timed",
                    0.0
                ],
                [
                    "out",
                    0.0
                ]
            ]
        },
        "nimbus": {
            "confidence": 5.6801949540385976e-05,
            "features": [
                [
                    "timestamp",
                    0.0
                ],
                [
                    "failed",
                    0.0
                ],
                [
                    "at",
                    0.0
                ],
                [
                    "play",
                    0.0
                ],
                [
                    "vmxnet",
                    0.0
                ],
                [
                    "number",
                    0.0
                ],
                [
                    "network",
                    0.0
                ],
                [
                    "device",
                    0.0
                ],
                [
                    "ops",
                    0.0
                ],
                [
                    "timestamp",
                    0.0
                ],
                [
                    "task",
                    0.0
                ],
                [
                    "apply",
                    0.0
                ],
                [
                    "net",
                    0.0
                ],
                [
                    "plan",
                    0.0
                ],
                [
                    "configuration",
                    0.0
                ],
                [
                    "file",
                    0.0
                ],
                [
                    "for",
                    0.0
                ],
                [
                    "new",
                    0.0
                ],
                [
                    "added",
                    0.0
                ],
                [
                    "nic",
                    0.0
                ],
                [
                    "in",
                    0.0
                ],
                [
                    "ubuntu",
                    0.0
                ],
                [
                    "fatal",
                    0.0
                ],
                [
                    "localhost",
                    0.0
                ],
                [
                    "failed",
                    0.0
                ],
                [
                    "failed",
                    0.0
                ],
                [
                    "to",
                    0.0
                ],
                [
                    "connect",
                    0.0
                ],
                [
                    "to",
                    0.0
                ],
                [
                    "the",
                    0.0
                ],
                [
                    "host",
                    0.0
                ],
                [
                    "via",
                    0.0
                ],
                [
                    "ssh",
                    0.0
                ],
                [
                    "ssh",
                    0.0
                ],
                [
                    "connect",
                    0.0
                ],
                [
                    "to",
                    0.0
                ],
                [
                    "host",
                    0.0
                ],
                [
                    "ip",
                    0.0
                ],
                [
                    "address",
                    0.0
                ],
                [
                    "port",
                    0.0
                ],
                [
                    "number",
                    0.0
                ],
                [
                    "connection",
                    0.0
                ],
                [
                    "timed",
                    0.0
                ],
                [
                    "out",
                    0.0
                ]
            ]
        },
        "testcase": {
            "confidence": 4.199599788989872e-05,
            "features": [
                [
                    "timestamp",
                    -0.01020564341661689
                ],
                [
                    "failed",
                    0.07990727324168327
                ],
                [
                    "at",
                    0.06448349533139512
                ],
                [
                    "play",
                    -0.005567115171510808
                ],
                [
                    "vmxnet",
                    -0.020842747562413794
                ],
                [
                    "number",
                    -0.0054680843910539685
                ],
                [
                    "network",
                    -0.07950364081096234
                ],
                [
                    "device",
                    -0.018100780975843465
                ],
                [
                    "ops",
                    0.038426357864102784
                ],
                [
                    "timestamp",
                    -0.05869342783164828
                ],
                [
                    "task",
                    0.022938749014344575
                ],
                [
                    "apply",
                    0.02078708205485166
                ],
                [
                    "net",
                    0.005307663224293165
                ],
                [
                    "plan",
                    0.026411780997005373
                ],
                [
                    "configuration",
                    -0.04244545758266309
                ],
                [
                    "file",
                    0.0654620780027294
                ],
                [
                    "for",
                    -0.041873974411704304
                ],
                [
                    "new",
                    -0.034999045619741626
                ],
                [
                    "added",
                    0.05508761544569555
                ],
                [
                    "nic",
                    -0.08261627845126529
                ],
                [
                    "in",
                    -0.05549192319620087
                ],
                [
                    "ubuntu",
                    -0.04365601137197369
                ],
                [
                    "fatal",
                    0.051876570451315614
                ],
                [
                    "localhost",
                    0.03195063113950868
                ],
                [
                    "failed",
                    -0.02644667029977636
                ],
                [
                    "failed",
                    0.030804532934774705
                ],
                [
                    "to",
                    -0.07434792239316856
                ],
                [
                    "connect",
                    -0.04087536560723408
                ],
                [
                    "to",
                    -0.0302197732652886
                ],
                [
                    "the",
                    -0.04070452187285723
                ],
                [
                    "host",
                    0.02845367360409293
                ],
                [
                    "via",
                    -0.19547388872284138
                ],
                [
                    "ssh",
                    0.03657168041667519
                ],
                [
                    "ssh",
                    0.0031745822804537136
                ],
                [
                    "connect",
                    -0.09958461119270019
                ],
                [
                    "to",
                    0.01955747447418005
                ],
                [
                    "host",
                    -0.006718290194711517
                ],
                [
                    "ip",
                    0.024227247782240568
                ],
                [
                    "address",
                    -0.0774083062775649
                ],
                [
                    "port",
                    -0.05499233467832736
                ],
                [
                    "number",
                    0.045801087064937594
                ],
                [
                    "connection",
                    -0.11149243458489588
                ],
                [
                    "timed",
                    -0.0434234565786616
                ],
                [
                    "out",
                    -0.05425293812695004
                ]
            ]
        },
        "usererror": {
            "confidence": 3.456180638750084e-05,
            "features": [
                [
                    "timestamp",
                    0.0
                ],
                [
                    "failed",
                    0.0
                ],
                [
                    "at",
                    0.0
                ],
                [
                    "play",
                    0.0
                ],
                [
                    "vmxnet",
                    0.0
                ],
                [
                    "number",
                    0.0
                ],
                [
                    "network",
                    0.0
                ],
                [
                    "device",
                    0.0
                ],
                [
                    "ops",
                    0.0
                ],
                [
                    "timestamp",
                    0.0
                ],
                [
                    "task",
                    0.0
                ],
                [
                    "apply",
                    0.0
                ],
                [
                    "net",
                    0.0
                ],
                [
                    "plan",
                    0.0
                ],
                [
                    "configuration",
                    0.0
                ],
                [
                    "file",
                    0.0
                ],
                [
                    "for",
                    0.0
                ],
                [
                    "new",
                    0.0
                ],
                [
                    "added",
                    0.0
                ],
                [
                    "nic",
                    0.0
                ],
                [
                    "in",
                    0.0
                ],
                [
                    "ubuntu",
                    0.0
                ],
                [
                    "fatal",
                    0.0
                ],
                [
                    "localhost",
                    0.0
                ],
                [
                    "failed",
                    0.0
                ],
                [
                    "failed",
                    0.0
                ],
                [
                    "to",
                    0.0
                ],
                [
                    "connect",
                    0.0
                ],
                [
                    "to",
                    0.0
                ],
                [
                    "the",
                    0.0
                ],
                [
                    "host",
                    0.0
                ],
                [
                    "via",
                    0.0
                ],
                [
                    "ssh",
                    0.0
                ],
                [
                    "ssh",
                    0.0
                ],
                [
                    "connect",
                    0.0
                ],
                [
                    "to",
                    0.0
                ],
                [
                    "host",
                    0.0
                ],
                [
                    "ip",
                    0.0
                ],
                [
                    "address",
                    0.0
                ],
                [
                    "port",
                    0.0
                ],
                [
                    "number",
                    0.0
                ],
                [
                    "connection",
                    0.0
                ],
                [
                    "timed",
                    0.0
                ],
                [
                    "out",
                    0.0
                ]
            ]
        },
        "product": {
            "confidence": 2.9469951186911203e-05,
            "features": [
                [
                    "timestamp",
                    0.008190118958355783
                ],
                [
                    "failed",
                    0.0026228068051706707
                ],
                [
                    "at",
                    -0.023743409050755202
                ],
                [
                    "play",
                    -0.005645415051654677
                ],
                [
                    "vmxnet",
                    -0.055312185066399316
                ],
                [
                    "number",
                    -0.006968337780962657
                ],
                [
                    "network",
                    -0.010663175091801017
                ],
                [
                    "device",
                    0.012059064468515469
                ],
                [
                    "ops",
                    0.015960977786572027
                ],
                [
                    "timestamp",
                    0.002512729817774938
                ],
                [
                    "task",
                    0.0004895910079648231
                ],
                [
                    "apply",
                    0.022764587615017675
                ],
                [
                    "net",
                    -0.017020158033760203
                ],
                [
                    "plan",
                    0.03503859783946308
                ],
                [
                    "configuration",
                    0.006551034229809655
                ],
                [
                    "file",
                    0.028152678945257
                ],
                [
                    "for",
                    -0.03792969354248109
                ],
                [
                    "new",
                    -0.03391373538839169
                ],
                [
                    "added",
                    0.04713798543934757
                ],
                [
                    "nic",
                    0.00416679359418624
                ],
                [
                    "in",
                    0.041017638417626096
                ],
                [
                    "ubuntu",
                    0.05258916237160857
                ],
                [
                    "fatal",
                    -0.0255928647392577
                ],
                [
                    "localhost",
                    -0.020019555331363362
                ],
                [
                    "failed",
                    -0.03846368819643118
                ],
                [
                    "failed",
                    0.005037736100492085
                ],
                [
                    "to",
                    0.005783338708498495
                ],
                [
                    "connect",
                    -0.0445544617609066
                ],
                [
                    "to",
                    -0.0063877111544456385
                ],
                [
                    "the",
                    -0.007604529084379325
                ],
                [
                    "host",
                    0.044221906008134484
                ],
                [
                    "via",
                    -0.00048186067726122423
                ],
                [
                    "ssh",
                    0.03269343542559759
                ],
                [
                    "ssh",
                    0.010264695370306338
                ],
                [
                    "connect",
                    -0.06278433900973684
                ],
                [
                    "to",
                    -0.03403202051909166
                ],
                [
                    "host",
                    -0.03010334378453686
                ],
                [
                    "ip",
                    0.014737106956587233
                ],
                [
                    "address",
                    -0.017691809544882975
                ],
                [
                    "port",
                    -0.02383080129185889
                ],
                [
                    "number",
                    -0.009003315652340999
                ],
                [
                    "connection",
                    -0.014383076176201118
                ],
                [
                    "timed",
                    0.0013518873780472636
                ],
                [
                    "out",
                    -0.032390964872778295
                ]
            ]
        },
        "testbed": {
            "confidence": 2.5103156076511368e-05,
            "features": [
                [
                    "timestamp",
                    0.0
                ],
                [
                    "failed",
                    0.0
                ],
                [
                    "at",
                    0.0
                ],
                [
                    "play",
                    0.0
                ],
                [
                    "vmxnet",
                    0.0
                ],
                [
                    "number",
                    0.0
                ],
                [
                    "network",
                    0.0
                ],
                [
                    "device",
                    0.0
                ],
                [
                    "ops",
                    0.0
                ],
                [
                    "timestamp",
                    0.0
                ],
                [
                    "task",
                    0.0
                ],
                [
                    "apply",
                    0.0
                ],
                [
                    "net",
                    0.0
                ],
                [
                    "plan",
                    0.0
                ],
                [
                    "configuration",
                    0.0
                ],
                [
                    "file",
                    0.0
                ],
                [
                    "for",
                    0.0
                ],
                [
                    "new",
                    0.0
                ],
                [
                    "added",
                    0.0
                ],
                [
                    "nic",
                    0.0
                ],
                [
                    "in",
                    0.0
                ],
                [
                    "ubuntu",
                    0.0
                ],
                [
                    "fatal",
                    0.0
                ],
                [
                    "localhost",
                    0.0
                ],
                [
                    "failed",
                    0.0
                ],
                [
                    "failed",
                    0.0
                ],
                [
                    "to",
                    0.0
                ],
                [
                    "connect",
                    0.0
                ],
                [
                    "to",
                    0.0
                ],
                [
                    "the",
                    0.0
                ],
                [
                    "host",
                    0.0
                ],
                [
                    "via",
                    0.0
                ],
                [
                    "ssh",
                    0.0
                ],
                [
                    "ssh",
                    0.0
                ],
                [
                    "connect",
                    0.0
                ],
                [
                    "to",
                    0.0
                ],
                [
                    "host",
                    0.0
                ],
                [
                    "ip",
                    0.0
                ],
                [
                    "address",
                    0.0
                ],
                [
                    "port",
                    0.0
                ],
                [
                    "number",
                    0.0
                ],
                [
                    "connection",
                    0.0
                ],
                [
                    "timed",
                    0.0
                ],
                [
                    "out",
                    0.0
                ]
            ]
        }
    }
}